beetlebox/__init__.py
beetlebox/admin.py
beetlebox/gmail_api.py
beetlebox/persist.py
beetlebox-0.0.4.dist-info/METADATA
beetlebox-0.0.4.dist-info/WHEEL
beetlebox-0.0.4.dist-info/licenses/LICENSE.txt
beetlebox-0.0.4.dist-info/RECORD
